PyE2/__init__.py
PyE2/_ver.py
PyE2/base_decentra_object.py
PyE2/plugins_manager_mixin.py
PyE2/base/__init__.py
PyE2/base/distributed_custom_code_presets.py
PyE2/base/generic_session.py
PyE2/base/instance.py
PyE2/base/pipeline.py
PyE2/base/plugin_template.py
PyE2/base/responses.py
PyE2/base/transaction.py
PyE2/base/payload/__init__.py
PyE2/base/payload/payload.py
PyE2/bc/__init__.py
PyE2/bc/base.py
PyE2/bc/chain.py
PyE2/bc/ec.py
PyE2/certs/__init__.py
PyE2/certs/r9092118.ala.eu-central-1.emqxsl.com.crt
PyE2/code_cheker/__init__.py
PyE2/code_cheker/base.py
PyE2/code_cheker/checker.py
PyE2/comm/__init__.py
PyE2/comm/amqp_wrapper.py
PyE2/comm/mqtt_wrapper.py
PyE2/const/README.md
PyE2/const/__init__.py
PyE2/const/base.py
PyE2/const/comms.py
PyE2/const/environment.py
PyE2/const/formatter.py
PyE2/const/heartbeat.py
PyE2/const/misc.py
PyE2/const/payload.py
PyE2/default/__init__.py
PyE2/default/instance/__init__.py
PyE2/default/instance/chain_dist_custom_job_01_plugin.py
PyE2/default/instance/custom_web_app_01_plugin.py
PyE2/default/instance/net_mon_01_plugin.py
PyE2/default/instance/view_scene_01_plugin.py
PyE2/default/session/mqtt_session.py
PyE2/io_formatter/__init__.py
PyE2/io_formatter/io_formatter_manager.py
PyE2/io_formatter/base/__init__.py
PyE2/io_formatter/base/base_formatter.py
PyE2/io_formatter/default/__init__.py
PyE2/io_formatter/default/a_dummy.py
PyE2/io_formatter/default/aixp1.py
PyE2/io_formatter/default/default.py
PyE2/logging/__init__.py
PyE2/logging/base_logger.py
PyE2/logging/small_logger.py
PyE2/logging/logger_mixins/__init__.py
PyE2/logging/logger_mixins/class_instance_mixin.py
PyE2/logging/logger_mixins/computer_vision_mixin.py
PyE2/logging/logger_mixins/datetime_mixin.py
PyE2/logging/logger_mixins/download_mixin.py
PyE2/logging/logger_mixins/general_serialization_mixin.py
PyE2/logging/logger_mixins/json_serialization_mixin.py
PyE2/logging/logger_mixins/pickle_serialization_mixin.py
PyE2/logging/logger_mixins/process_mixin.py
pye2-1.1.39.dist-info/METADATA
pye2-1.1.39.dist-info/WHEEL
pye2-1.1.39.dist-info/licenses/LICENSE
pye2-1.1.39.dist-info/RECORD
