Metadata-Version: 2.3
Name: PyE2
Version: 1.1.39
Summary: PyE2 is the Python SDK required for client app development in the Naeural network
Project-URL: Homepage, https://github.com/NaeuralEdgeProtocol/PyE2
Project-URL: Bug Tracker, https://github.com/NaeuralEdgeProtocol/PyE2/issues
Author-email: Stefan Saraev <saraevstefan@gmail.com>, Andrei Ionut Damian <andrei.damian@me.com>, Cristan Bleotiu <cristibleotiu@gmail.com>
License-File: LICENSE
Classifier: License :: OSI Approved :: MIT License
Classifier: Operating System :: OS Independent
Classifier: Programming Language :: Python :: 3
Requires-Python: >=3.8
Requires-Dist: cryptography>=39.0.0
Requires-Dist: numpy
Requires-Dist: paho-mqtt
Requires-Dist: pika
Requires-Dist: pyaml
Requires-Dist: pyopenssl>=23.0.0
Requires-Dist: python-dateutil
